Metadata-Version: 1.0
Name: HTOL
Version: 0.1.3
Summary: HTOL package
Home-page: https://github.imec.be/vsever71/HTOL
Author: Koen Van Sever
Author-email: koen.vansever@imec.be
License: UNKNOWN
Platform: UNKNOWN
